MANIFEST.in
README.rst
setup.py
src/zc/__init__.py
src/zc.zodbwsgi.egg-info/PKG-INFO
src/zc.zodbwsgi.egg-info/SOURCES.txt
src/zc.zodbwsgi.egg-info/dependency_links.txt
src/zc.zodbwsgi.egg-info/entry_points.txt
src/zc.zodbwsgi.egg-info/namespace_packages.txt
src/zc.zodbwsgi.egg-info/not-zip-safe
src/zc.zodbwsgi.egg-info/requires.txt
src/zc.zodbwsgi.egg-info/top_level.txt
src/zc/zodbwsgi/README.rst
src/zc/zodbwsgi/__init__.py
src/zc/zodbwsgi/tests.py