Metadata-Version: 1.0
Name: zc.zodbwsgi
Version: 1.0.0
Summary: .. image:: https://travis-ci.org/zopefoundation/zc.zodbwsgi.png?branch=master
Home-page: UNKNOWN
Author: Jim Fulton
Author-email: jim@zope.com
License: ZPL 2.1
Platform: UNKNOWN
